pyvm.py
python_version_manager-2024.5.dist-info/METADATA
python_version_manager-2024.5.dist-info/WHEEL
python_version_manager-2024.5.dist-info/entry_points.txt
python_version_manager-2024.5.dist-info/licenses/LICENSE
python_version_manager-2024.5.dist-info/RECORD
