Metadata-Version: 2.1
Name: python-version-manager
Version: 2024.5
Summary: dead-simple python version manager powered by python-build-standalone
Project-URL: Repository, https://github.com/alextremblay/pyvm
Project-URL: Homepage, https://alextremblay.github.io/pyvm/
Author-email: Alex Tremblay <alex.tremblay@utoronto.ca>
License: MIT
Requires-Python: >=3.6
